{
  "routes": {
    "/about": {},
    "/contact": {},
    "/pokemons/1": {},
    "/pokemons/10": {},
    "/pokemons/100": {},
    "/pokemons/101": {},
    "/pokemons/102": {},
    "/pokemons/103": {},
    "/pokemons/104": {},
    "/pokemons/105": {},
    "/pokemons/106": {},
    "/pokemons/107": {},
    "/pokemons/108": {},
    "/pokemons/109": {},
    "/pokemons/11": {},
    "/pokemons/110": {},
    "/pokemons/111": {},
    "/pokemons/112": {},
    "/pokemons/113": {},
    "/pokemons/114": {},
    "/pokemons/115": {},
    "/pokemons/116": {},
    "/pokemons/117": {},
    "/pokemons/118": {},
    "/pokemons/119": {},
    "/pokemons/12": {},
    "/pokemons/120": {},
    "/pokemons/121": {},
    "/pokemons/122": {},
    "/pokemons/123": {},
    "/pokemons/124": {},
    "/pokemons/125": {},
    "/pokemons/126": {},
    "/pokemons/127": {},
    "/pokemons/128": {},
    "/pokemons/129": {},
    "/pokemons/13": {},
    "/pokemons/130": {},
    "/pokemons/131": {},
    "/pokemons/132": {},
    "/pokemons/133": {},
    "/pokemons/134": {},
    "/pokemons/135": {},
    "/pokemons/136": {},
    "/pokemons/137": {},
    "/pokemons/138": {},
    "/pokemons/139": {},
    "/pokemons/14": {},
    "/pokemons/140": {},
    "/pokemons/141": {},
    "/pokemons/142": {},
    "/pokemons/143": {},
    "/pokemons/144": {},
    "/pokemons/145": {},
    "/pokemons/146": {},
    "/pokemons/147": {},
    "/pokemons/148": {},
    "/pokemons/149": {},
    "/pokemons/15": {},
    "/pokemons/150": {},
    "/pokemons/151": {},
    "/pokemons/152": {},
    "/pokemons/153": {},
    "/pokemons/154": {},
    "/pokemons/155": {},
    "/pokemons/156": {},
    "/pokemons/157": {},
    "/pokemons/158": {},
    "/pokemons/159": {},
    "/pokemons/16": {},
    "/pokemons/160": {},
    "/pokemons/161": {},
    "/pokemons/162": {},
    "/pokemons/163": {},
    "/pokemons/164": {},
    "/pokemons/165": {},
    "/pokemons/166": {},
    "/pokemons/167": {},
    "/pokemons/168": {},
    "/pokemons/169": {},
    "/pokemons/17": {},
    "/pokemons/170": {},
    "/pokemons/171": {},
    "/pokemons/172": {},
    "/pokemons/173": {},
    "/pokemons/174": {},
    "/pokemons/175": {},
    "/pokemons/176": {},
    "/pokemons/177": {},
    "/pokemons/178": {},
    "/pokemons/179": {},
    "/pokemons/18": {},
    "/pokemons/180": {},
    "/pokemons/181": {},
    "/pokemons/182": {},
    "/pokemons/183": {},
    "/pokemons/184": {},
    "/pokemons/185": {},
    "/pokemons/186": {},
    "/pokemons/187": {},
    "/pokemons/188": {},
    "/pokemons/189": {},
    "/pokemons/19": {},
    "/pokemons/190": {},
    "/pokemons/191": {},
    "/pokemons/192": {},
    "/pokemons/193": {},
    "/pokemons/194": {},
    "/pokemons/195": {},
    "/pokemons/196": {},
    "/pokemons/197": {},
    "/pokemons/198": {},
    "/pokemons/199": {},
    "/pokemons/2": {},
    "/pokemons/20": {},
    "/pokemons/200": {},
    "/pokemons/201": {},
    "/pokemons/202": {},
    "/pokemons/203": {},
    "/pokemons/204": {},
    "/pokemons/205": {},
    "/pokemons/206": {},
    "/pokemons/207": {},
    "/pokemons/208": {},
    "/pokemons/209": {},
    "/pokemons/21": {},
    "/pokemons/210": {},
    "/pokemons/211": {},
    "/pokemons/212": {},
    "/pokemons/213": {},
    "/pokemons/214": {},
    "/pokemons/215": {},
    "/pokemons/216": {},
    "/pokemons/217": {},
    "/pokemons/218": {},
    "/pokemons/219": {},
    "/pokemons/22": {},
    "/pokemons/220": {},
    "/pokemons/221": {},
    "/pokemons/222": {},
    "/pokemons/223": {},
    "/pokemons/224": {},
    "/pokemons/225": {},
    "/pokemons/226": {},
    "/pokemons/227": {},
    "/pokemons/228": {},
    "/pokemons/229": {},
    "/pokemons/23": {},
    "/pokemons/230": {},
    "/pokemons/231": {},
    "/pokemons/232": {},
    "/pokemons/233": {},
    "/pokemons/234": {},
    "/pokemons/235": {},
    "/pokemons/236": {},
    "/pokemons/237": {},
    "/pokemons/238": {},
    "/pokemons/239": {},
    "/pokemons/24": {},
    "/pokemons/240": {},
    "/pokemons/241": {},
    "/pokemons/242": {},
    "/pokemons/243": {},
    "/pokemons/244": {},
    "/pokemons/245": {},
    "/pokemons/246": {},
    "/pokemons/247": {},
    "/pokemons/248": {},
    "/pokemons/249": {},
    "/pokemons/25": {},
    "/pokemons/250": {},
    "/pokemons/251": {},
    "/pokemons/252": {},
    "/pokemons/253": {},
    "/pokemons/254": {},
    "/pokemons/255": {},
    "/pokemons/256": {},
    "/pokemons/257": {},
    "/pokemons/258": {},
    "/pokemons/259": {},
    "/pokemons/26": {},
    "/pokemons/260": {},
    "/pokemons/261": {},
    "/pokemons/262": {},
    "/pokemons/263": {},
    "/pokemons/264": {},
    "/pokemons/265": {},
    "/pokemons/266": {},
    "/pokemons/267": {},
    "/pokemons/268": {},
    "/pokemons/269": {},
    "/pokemons/27": {},
    "/pokemons/270": {},
    "/pokemons/271": {},
    "/pokemons/272": {},
    "/pokemons/273": {},
    "/pokemons/274": {},
    "/pokemons/275": {},
    "/pokemons/276": {},
    "/pokemons/277": {},
    "/pokemons/278": {},
    "/pokemons/279": {},
    "/pokemons/28": {},
    "/pokemons/280": {},
    "/pokemons/281": {},
    "/pokemons/282": {},
    "/pokemons/283": {},
    "/pokemons/284": {},
    "/pokemons/285": {},
    "/pokemons/286": {},
    "/pokemons/287": {},
    "/pokemons/288": {},
    "/pokemons/289": {},
    "/pokemons/29": {},
    "/pokemons/290": {},
    "/pokemons/291": {},
    "/pokemons/292": {},
    "/pokemons/293": {},
    "/pokemons/294": {},
    "/pokemons/295": {},
    "/pokemons/296": {},
    "/pokemons/297": {},
    "/pokemons/298": {},
    "/pokemons/299": {},
    "/pokemons/3": {},
    "/pokemons/30": {},
    "/pokemons/300": {},
    "/pokemons/31": {},
    "/pokemons/32": {},
    "/pokemons/33": {},
    "/pokemons/34": {},
    "/pokemons/35": {},
    "/pokemons/36": {},
    "/pokemons/37": {},
    "/pokemons/38": {},
    "/pokemons/39": {},
    "/pokemons/4": {},
    "/pokemons/40": {},
    "/pokemons/41": {},
    "/pokemons/42": {},
    "/pokemons/43": {},
    "/pokemons/44": {},
    "/pokemons/45": {},
    "/pokemons/46": {},
    "/pokemons/47": {},
    "/pokemons/48": {},
    "/pokemons/49": {},
    "/pokemons/5": {},
    "/pokemons/50": {},
    "/pokemons/51": {},
    "/pokemons/52": {},
    "/pokemons/53": {},
    "/pokemons/54": {},
    "/pokemons/55": {},
    "/pokemons/56": {},
    "/pokemons/57": {},
    "/pokemons/58": {},
    "/pokemons/59": {},
    "/pokemons/6": {},
    "/pokemons/60": {},
    "/pokemons/61": {},
    "/pokemons/62": {},
    "/pokemons/63": {},
    "/pokemons/64": {},
    "/pokemons/65": {},
    "/pokemons/66": {},
    "/pokemons/67": {},
    "/pokemons/68": {},
    "/pokemons/69": {},
    "/pokemons/7": {},
    "/pokemons/70": {},
    "/pokemons/71": {},
    "/pokemons/72": {},
    "/pokemons/73": {},
    "/pokemons/74": {},
    "/pokemons/75": {},
    "/pokemons/76": {},
    "/pokemons/77": {},
    "/pokemons/78": {},
    "/pokemons/79": {},
    "/pokemons/8": {},
    "/pokemons/80": {},
    "/pokemons/81": {},
    "/pokemons/82": {},
    "/pokemons/83": {},
    "/pokemons/84": {},
    "/pokemons/85": {},
    "/pokemons/86": {},
    "/pokemons/87": {},
    "/pokemons/88": {},
    "/pokemons/89": {},
    "/pokemons/9": {},
    "/pokemons/90": {},
    "/pokemons/91": {},
    "/pokemons/92": {},
    "/pokemons/93": {},
    "/pokemons/94": {},
    "/pokemons/95": {},
    "/pokemons/96": {},
    "/pokemons/97": {},
    "/pokemons/98": {},
    "/pokemons/99": {},
    "/pokemons/abra": {},
    "/pokemons/aerodactyl": {},
    "/pokemons/aipom": {},
    "/pokemons/alakazam": {},
    "/pokemons/ampharos": {},
    "/pokemons/arbok": {},
    "/pokemons/arcanine": {},
    "/pokemons/ariados": {},
    "/pokemons/articuno": {},
    "/pokemons/azumarill": {},
    "/pokemons/azurill": {},
    "/pokemons/bayleef": {},
    "/pokemons/beautifly": {},
    "/pokemons/beedrill": {},
    "/pokemons/bellossom": {},
    "/pokemons/bellsprout": {},
    "/pokemons/blastoise": {},
    "/pokemons/blaziken": {},
    "/pokemons/blissey": {},
    "/pokemons/breloom": {},
    "/pokemons/bulbasaur": {},
    "/pokemons/butterfree": {},
    "/pokemons/cascoon": {},
    "/pokemons/caterpie": {},
    "/pokemons/celebi": {},
    "/pokemons/chansey": {},
    "/pokemons/charizard": {},
    "/pokemons/charmander": {},
    "/pokemons/charmeleon": {},
    "/pokemons/chikorita": {},
    "/pokemons/chinchou": {},
    "/pokemons/clefable": {},
    "/pokemons/clefairy": {},
    "/pokemons/cleffa": {},
    "/pokemons/cloyster": {},
    "/pokemons/combusken": {},
    "/pokemons/corsola": {},
    "/pokemons/crobat": {},
    "/pokemons/croconaw": {},
    "/pokemons/cubone": {},
    "/pokemons/cyndaquil": {},
    "/pokemons/delibird": {},
    "/pokemons/dewgong": {},
    "/pokemons/diglett": {},
    "/pokemons/ditto": {},
    "/pokemons/dodrio": {},
    "/pokemons/doduo": {},
    "/pokemons/donphan": {},
    "/pokemons/dragonair": {},
    "/pokemons/dragonite": {},
    "/pokemons/dratini": {},
    "/pokemons/drowzee": {},
    "/pokemons/dugtrio": {},
    "/pokemons/dunsparce": {},
    "/pokemons/dustox": {},
    "/pokemons/eevee": {},
    "/pokemons/ekans": {},
    "/pokemons/electabuzz": {},
    "/pokemons/electrode": {},
    "/pokemons/elekid": {},
    "/pokemons/entei": {},
    "/pokemons/espeon": {},
    "/pokemons/exeggcute": {},
    "/pokemons/exeggutor": {},
    "/pokemons/exploud": {},
    "/pokemons/farfetchd": {},
    "/pokemons/fearow": {},
    "/pokemons/feraligatr": {},
    "/pokemons/flaaffy": {},
    "/pokemons/flareon": {},
    "/pokemons/forretress": {},
    "/pokemons/furret": {},
    "/pokemons/gardevoir": {},
    "/pokemons/gastly": {},
    "/pokemons/gengar": {},
    "/pokemons/geodude": {},
    "/pokemons/girafarig": {},
    "/pokemons/gligar": {},
    "/pokemons/gloom": {},
    "/pokemons/golbat": {},
    "/pokemons/goldeen": {},
    "/pokemons/golduck": {},
    "/pokemons/golem": {},
    "/pokemons/granbull": {},
    "/pokemons/graveler": {},
    "/pokemons/grimer": {},
    "/pokemons/grovyle": {},
    "/pokemons/growlithe": {},
    "/pokemons/gyarados": {},
    "/pokemons/hariyama": {},
    "/pokemons/haunter": {},
    "/pokemons/heracross": {},
    "/pokemons/hitmonchan": {},
    "/pokemons/hitmonlee": {},
    "/pokemons/hitmontop": {},
    "/pokemons/ho-oh": {},
    "/pokemons/hoothoot": {},
    "/pokemons/hoppip": {},
    "/pokemons/horsea": {},
    "/pokemons/houndoom": {},
    "/pokemons/houndour": {},
    "/pokemons/hypno": {},
    "/pokemons/igglybuff": {},
    "/pokemons/ivysaur": {},
    "/pokemons/jigglypuff": {},
    "/pokemons/jolteon": {},
    "/pokemons/jumpluff": {},
    "/pokemons/jynx": {},
    "/pokemons/kabuto": {},
    "/pokemons/kabutops": {},
    "/pokemons/kadabra": {},
    "/pokemons/kakuna": {},
    "/pokemons/kangaskhan": {},
    "/pokemons/kingdra": {},
    "/pokemons/kingler": {},
    "/pokemons/kirlia": {},
    "/pokemons/koffing": {},
    "/pokemons/krabby": {},
    "/pokemons/lanturn": {},
    "/pokemons/lapras": {},
    "/pokemons/larvitar": {},
    "/pokemons/ledian": {},
    "/pokemons/ledyba": {},
    "/pokemons/lickitung": {},
    "/pokemons/linoone": {},
    "/pokemons/lombre": {},
    "/pokemons/lotad": {},
    "/pokemons/loudred": {},
    "/pokemons/ludicolo": {},
    "/pokemons/lugia": {},
    "/pokemons/machamp": {},
    "/pokemons/machoke": {},
    "/pokemons/machop": {},
    "/pokemons/magby": {},
    "/pokemons/magcargo": {},
    "/pokemons/magikarp": {},
    "/pokemons/magmar": {},
    "/pokemons/magnemite": {},
    "/pokemons/magneton": {},
    "/pokemons/makuhita": {},
    "/pokemons/mankey": {},
    "/pokemons/mantine": {},
    "/pokemons/mareep": {},
    "/pokemons/marill": {},
    "/pokemons/marowak": {},
    "/pokemons/marshtomp": {},
    "/pokemons/masquerain": {},
    "/pokemons/meganium": {},
    "/pokemons/meowth": {},
    "/pokemons/metapod": {},
    "/pokemons/mew": {},
    "/pokemons/mewtwo": {},
    "/pokemons/mightyena": {},
    "/pokemons/miltank": {},
    "/pokemons/misdreavus": {},
    "/pokemons/moltres": {},
    "/pokemons/mr-mime": {},
    "/pokemons/mudkip": {},
    "/pokemons/muk": {},
    "/pokemons/murkrow": {},
    "/pokemons/natu": {},
    "/pokemons/nidoking": {},
    "/pokemons/nidoqueen": {},
    "/pokemons/nidoran-f": {},
    "/pokemons/nidoran-m": {},
    "/pokemons/nidorina": {},
    "/pokemons/nidorino": {},
    "/pokemons/nincada": {},
    "/pokemons/ninetales": {},
    "/pokemons/ninjask": {},
    "/pokemons/noctowl": {},
    "/pokemons/nosepass": {},
    "/pokemons/nuzleaf": {},
    "/pokemons/octillery": {},
    "/pokemons/oddish": {},
    "/pokemons/omanyte": {},
    "/pokemons/omastar": {},
    "/pokemons/onix": {},
    "/pokemons/page/1": {},
    "/pokemons/page/10": {},
    "/pokemons/page/2": {},
    "/pokemons/page/3": {},
    "/pokemons/page/4": {},
    "/pokemons/page/5": {},
    "/pokemons/page/6": {},
    "/pokemons/page/7": {},
    "/pokemons/page/8": {},
    "/pokemons/page/9": {},
    "/pokemons/paras": {},
    "/pokemons/parasect": {},
    "/pokemons/pelipper": {},
    "/pokemons/persian": {},
    "/pokemons/phanpy": {},
    "/pokemons/pichu": {},
    "/pokemons/pidgeot": {},
    "/pokemons/pidgeotto": {},
    "/pokemons/pidgey": {},
    "/pokemons/pikachu": {},
    "/pokemons/piloswine": {},
    "/pokemons/pineco": {},
    "/pokemons/pinsir": {},
    "/pokemons/politoed": {},
    "/pokemons/poliwag": {},
    "/pokemons/poliwhirl": {},
    "/pokemons/poliwrath": {},
    "/pokemons/ponyta": {},
    "/pokemons/poochyena": {},
    "/pokemons/porygon": {},
    "/pokemons/porygon2": {},
    "/pokemons/primeape": {},
    "/pokemons/psyduck": {},
    "/pokemons/pupitar": {},
    "/pokemons/quagsire": {},
    "/pokemons/quilava": {},
    "/pokemons/qwilfish": {},
    "/pokemons/raichu": {},
    "/pokemons/raikou": {},
    "/pokemons/ralts": {},
    "/pokemons/rapidash": {},
    "/pokemons/raticate": {},
    "/pokemons/rattata": {},
    "/pokemons/remoraid": {},
    "/pokemons/rhydon": {},
    "/pokemons/rhyhorn": {},
    "/pokemons/sandshrew": {},
    "/pokemons/sandslash": {},
    "/pokemons/sceptile": {},
    "/pokemons/scizor": {},
    "/pokemons/scyther": {},
    "/pokemons/seadra": {},
    "/pokemons/seaking": {},
    "/pokemons/seedot": {},
    "/pokemons/seel": {},
    "/pokemons/sentret": {},
    "/pokemons/shedinja": {},
    "/pokemons/shellder": {},
    "/pokemons/shiftry": {},
    "/pokemons/shroomish": {},
    "/pokemons/shuckle": {},
    "/pokemons/silcoon": {},
    "/pokemons/skarmory": {},
    "/pokemons/skiploom": {},
    "/pokemons/skitty": {},
    "/pokemons/slaking": {},
    "/pokemons/slakoth": {},
    "/pokemons/slowbro": {},
    "/pokemons/slowking": {},
    "/pokemons/slowpoke": {},
    "/pokemons/slugma": {},
    "/pokemons/smeargle": {},
    "/pokemons/smoochum": {},
    "/pokemons/sneasel": {},
    "/pokemons/snorlax": {},
    "/pokemons/snubbull": {},
    "/pokemons/spearow": {},
    "/pokemons/spinarak": {},
    "/pokemons/squirtle": {},
    "/pokemons/stantler": {},
    "/pokemons/starmie": {},
    "/pokemons/staryu": {},
    "/pokemons/steelix": {},
    "/pokemons/sudowoodo": {},
    "/pokemons/suicune": {},
    "/pokemons/sunflora": {},
    "/pokemons/sunkern": {},
    "/pokemons/surskit": {},
    "/pokemons/swampert": {},
    "/pokemons/swellow": {},
    "/pokemons/swinub": {},
    "/pokemons/taillow": {},
    "/pokemons/tangela": {},
    "/pokemons/tauros": {},
    "/pokemons/teddiursa": {},
    "/pokemons/tentacool": {},
    "/pokemons/tentacruel": {},
    "/pokemons/togepi": {},
    "/pokemons/togetic": {},
    "/pokemons/torchic": {},
    "/pokemons/totodile": {},
    "/pokemons/treecko": {},
    "/pokemons/typhlosion": {},
    "/pokemons/tyranitar": {},
    "/pokemons/tyrogue": {},
    "/pokemons/umbreon": {},
    "/pokemons/unown": {},
    "/pokemons/ursaring": {},
    "/pokemons/vaporeon": {},
    "/pokemons/venomoth": {},
    "/pokemons/venonat": {},
    "/pokemons/venusaur": {},
    "/pokemons/victreebel": {},
    "/pokemons/vigoroth": {},
    "/pokemons/vileplume": {},
    "/pokemons/voltorb": {},
    "/pokemons/vulpix": {},
    "/pokemons/wartortle": {},
    "/pokemons/weedle": {},
    "/pokemons/weepinbell": {},
    "/pokemons/weezing": {},
    "/pokemons/whismur": {},
    "/pokemons/wigglytuff": {},
    "/pokemons/wingull": {},
    "/pokemons/wobbuffet": {},
    "/pokemons/wooper": {},
    "/pokemons/wurmple": {},
    "/pokemons/xatu": {},
    "/pokemons/yanma": {},
    "/pokemons/zapdos": {},
    "/pokemons/zigzagoon": {},
    "/pokemons/zubat": {},
    "/pricing": {}
  }
}